TS2CG/PCG
TS2CG/__init__.py
TS2CG/SOL
TS2CG/PLM
TS2CG/wrapper.py
TS2CG/MembraneBuilder/Job.cpp
TS2CG/MembraneBuilder/LMatrix.cpp
TS2CG/MembraneBuilder/Job.h
TS2CG/MembraneBuilder/Domain.cpp
TS2CG/MembraneBuilder/FlatPointMaker.cpp
TS2CG/MembraneBuilder/SHGeneric1DPBCPointMaker.h
TS2CG/MembraneBuilder/Cylinder.h
TS2CG/MembraneBuilder/inclusion.cpp
TS2CG/MembraneBuilder/Domain.h
TS2CG/MembraneBuilder/Argument.cpp
TS2CG/MembraneBuilder/PDBFile.h
TS2CG/MembraneBuilder/bead.h
TS2CG/MembraneBuilder/inclusion.h
TS2CG/MembraneBuilder/Wall.h
TS2CG/MembraneBuilder/GroFile.h
TS2CG/MembraneBuilder/GenDomains.cpp
TS2CG/MembraneBuilder/IndexFileReader.cpp
TS2CG/MembraneBuilder/GenerateUnitCells.cpp
TS2CG/MembraneBuilder/Tensor2.h
TS2CG/MembraneBuilder/exclusion.cpp
TS2CG/MembraneBuilder/Vec3D.h
TS2CG/MembraneBuilder/point.h
TS2CG/MembraneBuilder/IndexFileReader.h
TS2CG/MembraneBuilder/BackMap.h
TS2CG/MembraneBuilder/help.cpp
TS2CG/MembraneBuilder/Nfunction.h
TS2CG/MembraneBuilder/SHGeneric1DPBCPointMaker.cpp
TS2CG/MembraneBuilder/PointBasedBlueprint.cpp
TS2CG/MembraneBuilder/GroFile.cpp
TS2CG/MembraneBuilder/IndexGroup.h
TS2CG/MembraneBuilder/Data_Structure.h
TS2CG/MembraneBuilder/LMatrix.h
TS2CG/MembraneBuilder/Sphere.h
TS2CG/MembraneBuilder/exclusion.h
TS2CG/MembraneBuilder/help.h
TS2CG/MembraneBuilder/Def.h
TS2CG/MembraneBuilder/GenerateUnitCells.h
TS2CG/MembraneBuilder/Tensor2.cpp
TS2CG/MembraneBuilder/ReadDTSFolder.h
TS2CG/MembraneBuilder/PDBFile.cpp
TS2CG/MembraneBuilder/ReadDTSFolder.cpp
TS2CG/MembraneBuilder/ReadLipidLibrary.h
TS2CG/MembraneBuilder/Cylinder.cpp
TS2CG/MembraneBuilder/Argument.h
TS2CG/MembraneBuilder/Nfunction.cpp
TS2CG/MembraneBuilder/BackMap.cpp
TS2CG/MembraneBuilder/point.cpp
TS2CG/MembraneBuilder/Sphere.cpp
TS2CG/MembraneBuilder/Vec3D.cpp
TS2CG/MembraneBuilder/IndexGroup.cpp
TS2CG/MembraneBuilder/FlatPointMaker.h
TS2CG/MembraneBuilder/UnitCell.h
TS2CG/MembraneBuilder/Wall.cpp
TS2CG-1.2.2.dist-info/entry_points.txt
TS2CG-1.2.2.dist-info/METADATA
TS2CG-1.2.2.dist-info/WHEEL
TS2CG-1.2.2.dist-info/LICENSE
TS2CG-1.2.2.dist-info/top_level.txt
TS2CG-1.2.2.dist-info/RECORD
