Metadata-Version: 2.1
Name: TS2CG
Version: 1.2.2
Summary: TS2CG: converts triangulated surfaces to coarse-grained membrane models
Author-email: Weria Pezeshkian <weria.pezeshkian@nbi.ku.dk>, Jan Stevens <j.a.stevens@rug.nl>
License: GNU GENERAL PUBLIC LICENSE
Requires-Python: >=3.6
License-File: LICENSE
